README.md
setup.py
bvr/__init__.py
bvr/bvr_compose.py
bvr/bvr_end.py
bvr/bvr_hi.py
bvr/bvr_repeat.py
bvr/bvr_rest.py
bvr/bvr_start.py
bvr/bvr_start_end.py
bvr/bvr_time.py
bvr/bvr_try.py
bvr/logger.py
bvr.egg-info/PKG-INFO
bvr.egg-info/SOURCES.txt
bvr.egg-info/dependency_links.txt
bvr.egg-info/top_level.txt
test/test_bvr_end.py
test/test_bvr_hi.py
test/test_bvr_repeat.py
test/test_bvr_rest_after.py
test/test_bvr_rest_before.py
test/test_bvr_rest_before_after.py
test/test_bvr_start.py
test/test_bvr_start_end.py
test/test_bvr_time.py