Metadata-Version: 2.1
Name: bvr
Version: 0.0.6
Summary: BVR: Log like a Beaver
Home-page: https://github.com/doedotdev/bvr
Author: doedotdev
Author-email: doedotdev@gmail.com
License: UNKNOWN
Platform: UNKNOWN
Classifier: Programming Language :: Python :: 3
Classifier: License :: OSI Approved :: MIT License
Classifier: Operating System :: OS Independent
